{"title":"Shikar","slug":"shikar","languages":["Odia"],"formats":["2D"],"kpi":{"cities":4,"gross":10881.0,"sold":69,"shows":6,"theatres":4,"states":2,"seats":1465,"occupancy":4.71,"fastfilling":0,"housefull":0},"formatSummary":[{"format":"2D","gross":10881.0,"sold":69,"seats":1465,"shows":6,"housefull":0,"fastfilling":0,"occupancy":4.71}],"languageSummary":[{"language":"Odia","gross":10881.0,"sold":69,"seats":1465,"shows":6,"housefull":0,"fastfilling":0,"occupancy":4.71}],"states":[{"state":"Odisha","theatres":3,"cities":3,"gross":10881.0,"sold":69,"seats":595,"shows":3,"housefull":0,"fastfilling":0,"occupancy":11.6,"cityList":[{"city":"Bhubaneshwar","theatres":1,"gross":10881.0,"sold":69,"seats":364,"shows":1,"housefull":0,"fastfilling":0,"occupancy":18.96,"theatreList":[{"venue":"Sriya Swati Stutee Cineplexx (4K, DOLBY ATMOS)","chain":"Sriya Swati Cine Complex Pvt Ltd","address":"Sriya Talkies Street, Janpath Road, Unit 3, Kharvela Nagar, Opposite ICICI Bank, Bhubaneshwar, Odisha 751001, India","gross":10881.0,"sold":69,"seats":364,"shows":1,"housefull":0,"fastfilling":0,"occupancy":18.96,"theatres":1,"showTimings":[{"time":"04:50 PM","audi":"SRIYA","format":"2D","totalSeats":364,"sold":69,"available":295,"occupancy":18.96,"estimatedCollection":10881.0,"maxGross":57401.22,"housefull":false,"fastfilling":false}]}]},{"city":"Jajpur Town (Odisha)","theatres":1,"gross":0.0,"sold":0,"seats":108,"shows":1,"housefull":0,"fastfilling":0,"occupancy":0.0,"theatreList":[{"venue":"Biraja Talkies (DOLBY 5.1 sound): Jajpur town","chain":"Biraja Talkies: Jajpur, Odisha","address":"Jajpur Singhpur Road, Near Hotel Kapila, Jajpur Town (Odisha), Odisha 755001, India","gross":0.0,"sold":0,"seats":108,"shows":1,"housefull":0,"fastfilling":0,"occupancy":0.0,"theatres":1,"showTimings":[{"time":"10:00 AM","audi":"","format":"2D","totalSeats":108,"sold":0,"available":108,"occupancy":0.0,"estimatedCollection":0.0,"maxGross":17031.13,"housefull":false,"fastfilling":false}]}]},{"city":"Rourkela","theatres":1,"gross":0.0,"sold":0,"seats":123,"shows":1,"housefull":0,"fastfilling":0,"occupancy":0.0,"theatreList":[{"venue":"Cinecaarnival: Crossroad Mall, Rourkela","chain":"BABA AKHANDALMANI ENTERPRISES","address":"5th Floor Cross Road Mall, Kachery Main Road, In Front of Rourkela Railway station, Rourkela, Odisha 769001, India","gross":0.0,"sold":0,"seats":123,"shows":1,"housefull":0,"fastfilling":0,"occupancy":0.0,"theatres":1,"showTimings":[{"time":"10:30 AM","audi":"DOLBY 7.1","format":"2D","totalSeats":123,"sold":0,"available":123,"occupancy":0.0,"estimatedCollection":0.0,"maxGross":19396.57,"housefull":false,"fastfilling":false}]}]}]},{"state":"Unknown","theatres":1,"cities":1,"gross":0.0,"sold":0,"seats":870,"shows":3,"housefull":0,"fastfilling":0,"occupancy":0.0,"cityList":[{"city":"Puri","theatres":1,"gross":0.0,"sold":0,"seats":870,"shows":3,"housefull":0,"fastfilling":0,"occupancy":0.0,"theatreList":[{"venue":"Apsara Cinema, Jogeswarpur","chain":"Ticketnew","address":"Apsara Talkies Jogeswarpur, Nayahat, Puri, Odisha 752107, India","gross":0.0,"sold":0,"seats":870,"shows":3,"housefull":0,"fastfilling":0,"occupancy":0.0,"theatres":1,"showTimings":[{"time":"03:00 PM","audi":"SCREEN1","format":"2D","totalSeats":290,"sold":0,"available":290,"occupancy":0.0,"estimatedCollection":0.0,"maxGross":45731.74,"housefull":false,"fastfilling":false},{"time":"06:00 PM","audi":"SCREEN1","format":"2D","totalSeats":290,"sold":0,"available":290,"occupancy":0.0,"estimatedCollection":0.0,"maxGross":45731.74,"housefull":false,"fastfilling":false},{"time":"12:00 PM","audi":"SCREEN1","format":"2D","totalSeats":290,"sold":0,"available":290,"occupancy":0.0,"estimatedCollection":0.0,"maxGross":45731.74,"housefull":false,"fastfilling":false}]}]}]}],"poster":{"thumb":"https://cdn.district.in/movies-assets/images/cinema/Shikar-poster-faef0490-6339-11f1-88d9-f137b99f53f9.jpg","bg":"https://cdn.district.in/movies-assets/images/cinema/Shikar-poster-faef0490-6339-11f1-88d9-f137b99f53f9.jpg"},"meta":{"genres":["Thriller","Suspense"],"runTime":"2h 00m","certification":"UA16+","languages":["Odia"],"likes":null,"eventCode":"223104","releaseDate":null,"cast":[],"trailer":null},"last_updated":"2026-07-17 16:02 IST"}