{"title":"Dark","slug":"dark","languages":["Tamil"],"formats":["2D"],"kpi":{"cities":8,"gross":441866.25,"sold":2834,"shows":42,"theatres":32,"states":2,"seats":7851,"occupancy":36.1,"fastfilling":10,"housefull":0},"formatSummary":[{"format":"2D","gross":441866.25,"sold":2834,"seats":7851,"shows":42,"housefull":0,"fastfilling":10,"occupancy":36.1}],"languageSummary":[{"language":"Tamil","gross":441866.25,"sold":2834,"seats":7851,"shows":42,"housefull":0,"fastfilling":10,"occupancy":36.1}],"states":[{"state":"Tamil Nadu","theatres":31,"cities":7,"gross":422396.25,"sold":2715,"seats":7668,"shows":41,"housefull":0,"fastfilling":9,"occupancy":35.41,"cityList":[{"city":"Chennai","theatres":22,"gross":341353.7,"sold":2218,"seats":5291,"shows":28,"housefull":0,"fastfilling":7,"occupancy":41.92,"theatreList":[{"venue":"PVR: VR Chennai, Anna Nagar","chain":"PVR","address":"3rd Floor, VR Mall, Metro Zone, No 44, Pillaiyar Koil Street, Jawaharlal Nehru Road, Anna Nagar, Chennai, Tamil Nadu 600040, India","gross":41892.6,"sold":273,"seats":404,"shows":2,"housefull":0,"fastfilling":1,"occupancy":67.57,"theatres":1,"showTimings":[{"time":"04:50 PM","audi":"","format":"2D","totalSeats":202,"sold":197,"available":5,"occupancy":97.52,"estimatedCollection":32066.2,"maxGross":32880.06,"housefull":false,"fastfilling":true},{"time":"10:00 PM","audi":"","format":"2D","totalSeats":202,"sold":76,"available":126,"occupancy":37.62,"estimatedCollection":9826.4,"maxGross":26117.54,"housefull":false,"fastfilling":false}]},{"venue":"PVR: Palazzo, The Nexus Vijaya Mall","chain":"PVR","address":"3rd Floor, 183, Arcot Road, Vadapalani, Nexus Mall, Chennai, Tamil Nadu 600026, India","gross":40831.3,"sold":263,"seats":545,"shows":2,"housefull":0,"fastfilling":1,"occupancy":48.26,"theatres":1,"showTimings":[{"time":"10:40 PM","audi":"","format":"2D","totalSeats":245,"sold":60,"available":185,"occupancy":24.49,"estimatedCollection":7921.2,"maxGross":32344.9,"housefull":false,"fastfilling":false},{"time":"12:15 PM","audi":"","format":"2D","totalSeats":300,"sold":203,"available":97,"occupancy":67.67,"estimatedCollection":32910.1,"maxGross":48635.62,"housefull":false,"fastfilling":true}]},{"venue":"PVR: Ampa Mall, Nelson Manickam Road","chain":"PVR","address":"4th Floor, Ampa Skywalk Mall, Nelson Manickam Road, Aminjikarai, Chennai, Tamil Nadu 600029, India","gross":33239.15,"sold":190,"seats":357,"shows":2,"housefull":0,"fastfilling":1,"occupancy":53.22,"theatres":1,"showTimings":[{"time":"03:25 PM","audi":"","format":"2D","totalSeats":210,"sold":150,"available":60,"occupancy":71.43,"estimatedCollection":25887.15,"maxGross":36242.01,"housefull":false,"fastfilling":true},{"time":"09:30 PM","audi":"","format":"2D","totalSeats":147,"sold":40,"available":107,"occupancy":27.21,"estimatedCollection":7352.0,"maxGross":27018.6,"housefull":false,"fastfilling":false}]},{"venue":"PVR: Grand Mall, Velachery","chain":"PVR","address":"3rd Floor, Grand Square Mall, No.137, Tambaram Velachery Road, V.O.C Nagar, Doctor Seetaram Nagar, Chennai, Tamil Nadu 600042, India","gross":31582.0,"sold":200,"seats":207,"shows":1,"housefull":0,"fastfilling":1,"occupancy":96.62,"theatres":1,"showTimings":[{"time":"03:25 PM","audi":"","format":"2D","totalSeats":207,"sold":200,"available":7,"occupancy":96.62,"estimatedCollection":31582.0,"maxGross":32687.37,"housefull":false,"fastfilling":true}]},{"venue":"PVR Ampa Skywalk Mall, Aminjikarai, Chennai","chain":"Pvr","address":"4th Floor, Ampa Skywalk Mall, Nelson Manickam Road, Aminjikarai, Chennai, Tamil Nadu 600029, India","gross":25478.05,"sold":152,"seats":357,"shows":2,"housefull":0,"fastfilling":1,"occupancy":42.58,"theatres":1,"showTimings":[{"time":"03:25 PM","audi":"AUDI 02","format":"2D","totalSeats":210,"sold":130,"available":80,"occupancy":61.9,"estimatedCollection":23635.1,"maxGross":38179.78,"housefull":false,"fastfilling":true},{"time":"09:30 PM","audi":"AUDI 07","format":"2D","totalSeats":147,"sold":22,"available":125,"occupancy":14.97,"estimatedCollection":1842.95,"maxGross":12314.26,"housefull":false,"fastfilling":false}]},{"venue":"AGS Cinemas: Maduravoyal","chain":"AGS Cinema","address":"No 3/47, Alapakkam Main Road, Subramaniapuram, Pallavan Nagar, Chennai, Tamil Nadu 600095, India","gross":20556.0,"sold":137,"seats":342,"shows":1,"housefull":0,"fastfilling":0,"occupancy":40.06,"theatres":1,"showTimings":[{"time":"05:05 PM","audi":"4K DOLBY ATMOS","format":"2D","totalSeats":342,"sold":137,"available":205,"occupancy":40.06,"estimatedCollection":20556.0,"maxGross":51314.98,"housefull":false,"fastfilling":false}]},{"venue":"Rohini Silver Screens: Koyambedu","chain":"Rohini Movie Park","address":"141/2, Poonamallee High Road, Koyembedu, Near St. Thomas College Of Arts And Science, Chennai, Tamil Nadu 600107, India","gross":19360.0,"sold":121,"seats":630,"shows":2,"housefull":0,"fastfilling":0,"occupancy":19.21,"theatres":1,"showTimings":[{"time":"11:59 PM","audi":"2K/DOLBY 7.1","format":"2D","totalSeats":315,"sold":40,"available":275,"occupancy":12.7,"estimatedCollection":6400.0,"maxGross":50400.0,"housefull":false,"fastfilling":false},{"time":"12:40 PM","audi":"2K/DOLBY 7.1","format":"2D","totalSeats":315,"sold":81,"available":234,"occupancy":25.71,"estimatedCollection":12960.0,"maxGross":50400.0,"housefull":false,"fastfilling":false}]},{"venue":"HDFC Millennia PVR: Escape-Express Avenue Mall","chain":"PVR","address":"3rd Floor, Whites Road, Express Mall, Chennai, Tamil Nadu 600014, India","gross":18242.65,"sold":107,"seats":110,"shows":1,"housefull":0,"fastfilling":1,"occupancy":97.27,"theatres":1,"showTimings":[{"time":"04:45 PM","audi":"","format":"2D","totalSeats":110,"sold":107,"available":3,"occupancy":97.27,"estimatedCollection":18242.65,"maxGross":18754.13,"housefull":false,"fastfilling":true}]},{"venue":"INOX National: Arcot Road","chain":"INOX","address":"Chandra Metro Mall, Arcot Road, Aranganathan Nagar, Valasaravakkam, Near Mega Mart, Chennai, Tamil Nadu 600092, India","gross":16868.1,"sold":96,"seats":197,"shows":1,"housefull":0,"fastfilling":0,"occupancy":48.73,"theatres":1,"showTimings":[{"time":"07:30 PM","audi":"Atmos","format":"2D","totalSeats":197,"sold":96,"available":101,"occupancy":48.73,"estimatedCollection":16868.1,"maxGross":34614.75,"housefull":false,"fastfilling":false}]},{"venue":"INOX National, Virugambakkam, Chennai","chain":"Pvr","address":"Metro Stationery, 3rd Floor, Chandra Metro Mall, Arcot Road, Virugambakkam, Chennai, Tamil Nadu 600092, India","gross":13531.05,"sold":87,"seats":197,"shows":1,"housefull":0,"fastfilling":0,"occupancy":44.16,"theatres":1,"showTimings":[{"time":"07:30 PM","audi":"SCREEN 5","format":"2D","totalSeats":197,"sold":87,"available":110,"occupancy":44.16,"estimatedCollection":13531.05,"maxGross":30639.27,"housefull":false,"fastfilling":false}]},{"venue":"PVR: Heritage RSL ECR, Chennai","chain":"PVR","address":"1st Floor, Near Uthandi Toll Gate, Survey No: 3/488B1A And 3/700 No.17. Uthandi Village, Sholinganallur Taluk, East Coast Road, Chennai, Tamil Nadu 600119, India","gross":11693.05,"sold":77,"seats":218,"shows":2,"housefull":0,"fastfilling":1,"occupancy":35.32,"theatres":1,"showTimings":[{"time":"03:20 PM","audi":"","format":"2D","totalSeats":109,"sold":62,"available":47,"occupancy":56.88,"estimatedCollection":10360.0,"maxGross":18213.55,"housefull":false,"fastfilling":true},{"time":"10:20 PM","audi":"","format":"2D","totalSeats":109,"sold":15,"available":94,"occupancy":13.76,"estimatedCollection":1333.05,"maxGross":9686.83,"housefull":false,"fastfilling":false}]},{"venue":"PVR: Grand Galada, Pallavaram","chain":"PVR","address":"Grand Galada Mall, Kohinoor-2, Officers Line, GST Road, Pallavaram, Arumalai Chavadi, Chennai, Tamil Nadu 600043, India","gross":11079.4,"sold":80,"seats":180,"shows":1,"housefull":0,"fastfilling":0,"occupancy":44.44,"theatres":1,"showTimings":[{"time":"12:45 PM","audi":"","format":"2D","totalSeats":180,"sold":80,"available":100,"occupancy":44.44,"estimatedCollection":11079.4,"maxGross":24928.65,"housefull":false,"fastfilling":false}]},{"venue":"INOX Phoenix Market City (formerly Jazz Cinemas), Velachery, Chennai","chain":"Pvr","address":"2nd Floor, Phoenix Market City,  Velachery Main Road, Velachery, Chennai, Tamil Nadu 600042, India","gross":10670.3,"sold":82,"seats":224,"shows":1,"housefull":0,"fastfilling":0,"occupancy":36.61,"theatres":1,"showTimings":[{"time":"10:30 PM","audi":"SCREEN 9","format":"2D","totalSeats":224,"sold":82,"available":142,"occupancy":36.61,"estimatedCollection":10670.3,"maxGross":29148.14,"housefull":false,"fastfilling":false}]},{"venue":"PVR: Sathyam, Royapettah","chain":"PVR","address":"8, Thiru Vi Ka Road, Royapettah, Chennai, Tamil Nadu 600014, India","gross":8317.45,"sold":53,"seats":114,"shows":1,"housefull":0,"fastfilling":0,"occupancy":46.49,"theatres":1,"showTimings":[{"time":"10:00 PM","audi":"","format":"2D","totalSeats":114,"sold":53,"available":61,"occupancy":46.49,"estimatedCollection":8317.45,"maxGross":17890.36,"housefull":false,"fastfilling":false}]},{"venue":"INOX: LUXE Phoenix Market City, Velachery","chain":"INOX","address":"Formerly Jazz Cinemas, 2nd Floor, Phoenix Market City, Velachery Main Road, Velachery, Chennai, Tamil Nadu 600042, India","gross":7913.3,"sold":67,"seats":224,"shows":1,"housefull":0,"fastfilling":0,"occupancy":29.91,"theatres":1,"showTimings":[{"time":"10:30 PM","audi":"Atmos","format":"2D","totalSeats":224,"sold":67,"available":157,"occupancy":29.91,"estimatedCollection":7913.3,"maxGross":26456.41,"housefull":false,"fastfilling":false}]},{"venue":"INOX: The Marina Mall, OMR","chain":"INOX","address":"3rd Floor, The Marina Mall, Old Mahabalipuram Road, Egatoor, Navalur, Chennai, Tamil Nadu 603103, India","gross":6984.4,"sold":38,"seats":153,"shows":1,"housefull":0,"fastfilling":0,"occupancy":24.84,"theatres":1,"showTimings":[{"time":"10:25 PM","audi":"","format":"2D","totalSeats":153,"sold":38,"available":115,"occupancy":24.84,"estimatedCollection":6984.4,"maxGross":28121.4,"housefull":false,"fastfilling":false}]},{"venue":"PVR: Aerohub, Chennai","chain":"PVR","address":"PVR Cinemas, 2nd Floor, Aerohub East Wing, MLCP Block, Chennai International Airport, GST Road, Meenambakkam, Chennai, Tamil Nadu 600027, India","gross":6334.2,"sold":57,"seats":182,"shows":1,"housefull":0,"fastfilling":0,"occupancy":31.32,"theatres":1,"showTimings":[{"time":"10:10 PM","audi":"","format":"2D","totalSeats":182,"sold":57,"available":125,"occupancy":31.32,"estimatedCollection":6334.2,"maxGross":20224.99,"housefull":false,"fastfilling":false}]},{"venue":"Cinepolis: BSR Mall, OMR, Thoraipakkam","chain":"Cinepolis","address":"BSR Mall, Thoraipakkam, Seevaram, Oggiyamduraipakkam, Chennai, Tamil Nadu 600097, India","gross":6199.8,"sold":45,"seats":169,"shows":1,"housefull":0,"fastfilling":0,"occupancy":26.63,"theatres":1,"showTimings":[{"time":"10:00 AM","audi":"","format":"2D","totalSeats":169,"sold":45,"available":124,"occupancy":26.63,"estimatedCollection":6199.8,"maxGross":23283.69,"housefull":false,"fastfilling":false}]},{"venue":"AGS Cinemas: Villivakkam","chain":"AGS Cinema","address":"No. 1/1, Mettu Street Villivakkam, Behind, Villivakkam Bus Depot, Chennai, Tamil Nadu 600049, India","gross":4008.0,"sold":36,"seats":194,"shows":1,"housefull":0,"fastfilling":0,"occupancy":18.56,"theatres":1,"showTimings":[{"time":"11:00 PM","audi":"4K DOLBY 7.1","format":"2D","totalSeats":194,"sold":36,"available":158,"occupancy":18.56,"estimatedCollection":4008.0,"maxGross":21598.67,"housefull":false,"fastfilling":false}]},{"venue":"PVR: SKLS Galaxy Mall, Red Hills Chennai","chain":"PVR","address":"4th Floor, SKLS Galaxy Mall, Survey No. 93/IC/2B, GNT Road Red Hills, Chennai, Tamil Nadu 600052, India","gross":3626.6,"sold":31,"seats":97,"shows":1,"housefull":0,"fastfilling":0,"occupancy":31.96,"theatres":1,"showTimings":[{"time":"09:25 AM","audi":"","format":"2D","totalSeats":97,"sold":31,"available":66,"occupancy":31.96,"estimatedCollection":3626.6,"maxGross":11347.75,"housefull":false,"fastfilling":false}]},{"venue":"Miraj Cinemas: Sekaran Mall, Perrumbakkam","chain":"Miraj Cinemas","address":"Sekaran Mall, 4th and 5th Floor, Survey No.452(3), Village Perumbakkam, Taluk Sholinganallur, Kancheepuram, Chennai, Tamil Nadu 600100, India","gross":1646.3,"sold":16,"seats":110,"shows":1,"housefull":0,"fastfilling":0,"occupancy":14.55,"theatres":1,"showTimings":[{"time":"10:40 PM","audi":"","format":"2D","totalSeats":110,"sold":16,"available":94,"occupancy":14.55,"estimatedCollection":1646.3,"maxGross":11318.31,"housefull":false,"fastfilling":false}]},{"venue":"Murugan Cinemas PLF 4K, Ambattur, Chennai","chain":"Murugan Cinemas","address":"No. 10, O.V. Alagesan Nagar, Near Ambattur Railway Station, Chennai, Tamil Nadu 600053, India","gross":1300.0,"sold":10,"seats":80,"shows":1,"housefull":0,"fastfilling":0,"occupancy":12.5,"theatres":1,"showTimings":[{"time":"02:15 PM","audi":"SAKTHI MURUGAN A/C 4K DOLBY ATMOS","format":"2D","totalSeats":80,"sold":10,"available":70,"occupancy":12.5,"estimatedCollection":1300.0,"maxGross":10400.0,"housefull":false,"fastfilling":false}]}]},{"city":"Coimbatore","theatres":3,"gross":53502.55,"sold":329,"seats":896,"shows":6,"housefull":0,"fastfilling":1,"occupancy":36.72,"theatreList":[{"venue":"INOX: Prozone Mall, Coimbatore","chain":"INOX","address":"S.F. No. 201, Sathy Main Road, Coimbatore, Tamil Nadu 641035, India","gross":23311.0,"sold":155,"seats":366,"shows":2,"housefull":0,"fastfilling":1,"occupancy":42.35,"theatres":1,"showTimings":[{"time":"04:10 PM","audi":"","format":"2D","totalSeats":170,"sold":103,"available":67,"occupancy":60.59,"estimatedCollection":16471.85,"maxGross":27186.55,"housefull":false,"fastfilling":true},{"time":"10:25 PM","audi":"","format":"2D","totalSeats":196,"sold":52,"available":144,"occupancy":26.53,"estimatedCollection":6839.15,"maxGross":25778.33,"housefull":false,"fastfilling":false}]},{"venue":"KG Cinemas: Coimbatore","chain":"K G Entertainment Co Pvt Ltd","address":"No.3, Bungalow Road, Race Course, Near K G Hospital, Coimbatore, Tamil Nadu 641018, India","gross":21840.5,"sold":118,"seats":369,"shows":3,"housefull":0,"fastfilling":0,"occupancy":31.98,"theatres":1,"showTimings":[{"time":"01:10 PM","audi":"","format":"2D","totalSeats":118,"sold":38,"available":80,"occupancy":32.2,"estimatedCollection":7596.05,"maxGross":23587.73,"housefull":false,"fastfilling":false},{"time":"04:05 PM","audi":"","format":"2D","totalSeats":118,"sold":51,"available":67,"occupancy":43.22,"estimatedCollection":9820.4,"maxGross":22721.71,"housefull":false,"fastfilling":false},{"time":"10:15 AM","audi":"PALLAVI","format":"2D","totalSeats":133,"sold":29,"available":104,"occupancy":21.8,"estimatedCollection":4424.05,"maxGross":20289.61,"housefull":false,"fastfilling":false}]},{"venue":"Broadway Cinemas: Coimbatore","chain":"Broadway Megaplex: Coimbatore","address":"96, Broadway Square, Off Avinashi Road, Civil Aerodrome Post, Coimbatore, Tamil Nadu 641014, India","gross":8351.05,"sold":56,"seats":161,"shows":1,"housefull":0,"fastfilling":0,"occupancy":34.78,"theatres":1,"showTimings":[{"time":"04:00 PM","audi":"4K DOLBY ATMOS","format":"2D","totalSeats":161,"sold":56,"available":105,"occupancy":34.78,"estimatedCollection":8351.05,"maxGross":24009.27,"housefull":false,"fastfilling":false}]}]},{"city":"Pondicherry","theatres":1,"gross":19470.0,"sold":119,"seats":229,"shows":1,"housefull":0,"fastfilling":1,"occupancy":51.97,"theatreList":[{"venue":"PVR: Providence Mall, Pondicherry","chain":"PVR","address":"No-7, Providence Mall, 4th and 5th Floor, Venkatasubba Reddiyar Salai, Via Cuddalore Road, Near Malai Malar, Pondicherry, Tamil Nadu 605001, India","gross":19470.0,"sold":119,"seats":229,"shows":1,"housefull":0,"fastfilling":1,"occupancy":51.97,"theatres":1,"showTimings":[{"time":"12:00 PM","audi":"","format":"2D","totalSeats":229,"sold":119,"available":110,"occupancy":51.97,"estimatedCollection":19470.0,"maxGross":37467.48,"housefull":false,"fastfilling":true}]}]},{"city":"Salem","theatres":2,"gross":3440.0,"sold":22,"seats":827,"shows":3,"housefull":0,"fastfilling":0,"occupancy":2.66,"theatreList":[{"venue":"ARRS Multiplex 4K Dolby Audio 7.1.2: Salem","chain":"ARRS Cinemas","address":"2-94-95, Meyyanoor Bye-pass Road, Meyyanoor, Near Srivari Shopping Mall, Salem, Tamil Nadu 636701, India","gross":1800.0,"sold":12,"seats":710,"shows":2,"housefull":0,"fastfilling":0,"occupancy":1.69,"theatres":1,"showTimings":[{"time":"02:45 PM","audi":"","format":"2D","totalSeats":355,"sold":2,"available":353,"occupancy":0.56,"estimatedCollection":300.0,"maxGross":53250.0,"housefull":false,"fastfilling":false},{"time":"10:45 PM","audi":"","format":"2D","totalSeats":355,"sold":10,"available":345,"occupancy":2.82,"estimatedCollection":1500.0,"maxGross":53250.0,"housefull":false,"fastfilling":false}]},{"venue":"SPR Cinecastle 4K(RGB) - 64Ch. Dolby Atmos: Salem","chain":"Rajavelu & CO","address":"16/476, Tharma Nagar,Rajaji Street, Salem, Tamil Nadu 636005, India","gross":1640.0,"sold":10,"seats":117,"shows":1,"housefull":0,"fastfilling":0,"occupancy":8.55,"theatres":1,"showTimings":[{"time":"02:50 PM","audi":"DOLBY 7.1","format":"2D","totalSeats":117,"sold":10,"available":107,"occupancy":8.55,"estimatedCollection":1640.0,"maxGross":19188.0,"housefull":false,"fastfilling":false}]}]},{"city":"Trichy","theatres":1,"gross":2890.0,"sold":17,"seats":126,"shows":1,"housefull":0,"fastfilling":0,"occupancy":13.49,"theatreList":[{"venue":"LA CINEMA: MARIS, TRICHY","chain":"Maris Cinema","address":"Maris Theater Complex, Fort Station Road, Trichy, Tamil Nadu 620002, India","gross":2890.0,"sold":17,"seats":126,"shows":1,"housefull":0,"fastfilling":0,"occupancy":13.49,"theatres":1,"showTimings":[{"time":"10:55 PM","audi":"4K","format":"2D","totalSeats":126,"sold":17,"available":109,"occupancy":13.49,"estimatedCollection":2890.0,"maxGross":21420.0,"housefull":false,"fastfilling":false}]}]},{"city":"Erode","theatres":1,"gross":1740.0,"sold":10,"seats":141,"shows":1,"housefull":0,"fastfilling":0,"occupancy":7.09,"theatreList":[{"venue":"Sri Sakthi Cinemas: Erode","chain":"Sri Sakthi Cinemas Tirupur","address":"Mettur Road, Municipal Colony, Edayankattuvalasu, Erode, Tamil Nadu 638001, India","gross":1740.0,"sold":10,"seats":141,"shows":1,"housefull":0,"fastfilling":0,"occupancy":7.09,"theatres":1,"showTimings":[{"time":"09:30 AM","audi":"DOLBY 7.1","format":"2D","totalSeats":141,"sold":10,"available":131,"occupancy":7.09,"estimatedCollection":1740.0,"maxGross":24534.0,"housefull":false,"fastfilling":false}]}]},{"city":"Tirupur","theatres":1,"gross":0.0,"sold":0,"seats":158,"shows":1,"housefull":0,"fastfilling":0,"occupancy":0.0,"theatreList":[{"venue":"Sri Sakthi Cinemas Multiplex: Tirupur","chain":"Sri Sakthi Cinemas Tirupur","address":"No 256, Union Mill Road, KPN Colony, Valipalayam, Near ABT PARCEL SERVICE Tirupur, Tirupur, Tamil Nadu 641601, India","gross":0.0,"sold":0,"seats":158,"shows":1,"housefull":0,"fastfilling":0,"occupancy":0.0,"theatres":1,"showTimings":[{"time":"09:00 AM","audi":"DOLBY 7.1","format":"2D","totalSeats":158,"sold":0,"available":158,"occupancy":0.0,"estimatedCollection":0.0,"maxGross":24634.75,"housefull":false,"fastfilling":false}]}]}]},{"state":"Puducherry","theatres":1,"cities":1,"gross":19470.0,"sold":119,"seats":183,"shows":1,"housefull":0,"fastfilling":1,"occupancy":65.03,"cityList":[{"city":"Puducherry","theatres":1,"gross":19470.0,"sold":119,"seats":183,"shows":1,"housefull":0,"fastfilling":1,"occupancy":65.03,"theatreList":[{"venue":"PVR Providence Mall, Providence Mall, Pondicherry","chain":"Pvr","address":"Providence Mall, 4th and 5th Floor, Venkatasubba Reddiyar Salai via Cuddalore Road, Near Malai Malar, Pondicherry, Tamil Nadu 605001,India","gross":19470.0,"sold":119,"seats":183,"shows":1,"housefull":0,"fastfilling":1,"occupancy":65.03,"theatres":1,"showTimings":[{"time":"12:00 PM","audi":"SCREEN 4","format":"2D","totalSeats":183,"sold":119,"available":64,"occupancy":65.03,"estimatedCollection":19470.0,"maxGross":29941.26,"housefull":false,"fastfilling":true}]}]}]}],"poster":{"thumb":"assets/posters/dark-thumb.jpg","bg":"assets/posters/dark-bg.jpg"},"meta":{"genres":["Thriller"],"runTime":"1h 50m","certification":"UA16+","languages":["Tamil"],"likes":null,"eventCode":"225502","releaseDate":null,"cast":[],"trailer":null},"last_updated":"2026-07-12 22:17 IST"}